dinja/api.py
dinja/core.py
dinja/main.py
dinja/parser.py
dinja/renderer.py
dinja/settings.py
dinja/storage.py
dinja_tool-0.2.0.dist-info/LICENSE.txt
dinja_tool-0.2.0.dist-info/METADATA
dinja_tool-0.2.0.dist-info/WHEEL
dinja_tool-0.2.0.dist-info/entry_points.txt
dinja_tool-0.2.0.dist-info/RECORD
