Metadata-Version: 2.3
Name: dinja-tool
Version: 0.2.0
Summary: Tool to create text files from DBML using Jinja2 templates.
License: EUPL-1.2
Keywords: dbml,jinja,template,code generation,database,schema
Author: Thomas Wesenigk
Author-email: aardjon@noreply.codeberg.org
Requires-Python: >=3.12
Classifier: Development Status :: 4 - Beta
Classifier: Environment :: Console
Classifier: Intended Audience :: Developers
Classifier: License :: OSI Approved :: European Union Public Licence 1.2 (EUPL 1.2)
Classifier: Programming Language :: Python :: 3
Classifier: Programming Language :: Python :: 3.12
Classifier: Topic :: Database
Classifier: Topic :: Documentation
Classifier: Topic :: Software Development
Classifier: Topic :: Software Development :: Code Generators
Classifier: Topic :: Utilities
Provides-Extra: dev
Requires-Dist: black ; extra == "dev"
Requires-Dist: isort ; extra == "dev"
Requires-Dist: jinja2
Requires-Dist: mypy ; extra == "dev"
Requires-Dist: pydbml
Requires-Dist: ruff ; extra == "dev"
Project-URL: Homepage, https://codeberg.org/Aardjon/dinja
Project-URL: Repository, https://codeberg.org/Aardjon/dinja.git
